slap2_utils/__init__.py
slap2_utils/datafile.py
slap2_utils/fast_line_data.c
slap2_utils/fast_line_data.cpython-310-x86_64-linux-gnu.so
slap2_utils/fast_line_data.cpython-311-x86_64-linux-gnu.so
slap2_utils/fast_line_data.cpython-312-x86_64-linux-gnu.so
slap2_utils/fast_line_data.cpython-39-x86_64-linux-gnu.so
slap2_utils/fast_line_data.pyx
slap2_utils/dataviewer/__init__.py
slap2_utils/dataviewer/cli.py
slap2_utils/dataviewer/dataviewer.py
slap2_utils/dataviewer/mainWindow.py
slap2_utils/dataviewer/pixelTraces.py
slap2_utils/dataviewer/roiPlot.py
slap2_utils/dataviewer/roiTraces.py
slap2_utils/dataviewer/plotWindows/allROITraces.py
slap2_utils/dataviewer/plotWindows/roiInspectPlot.py
slap2_utils/dataviewer/plotWindows/roiTracePlot.py
slap2_utils/dataviewer/plotWindows/roiViewer3D.py
slap2_utils/dataviewer/plotWindows/superPixPlot.py
slap2_utils/examples/3DExampleScan.dat
slap2_utils/examples/3DExampleScan.meta
slap2_utils/examples/SLAP2_Utils_example.ipynb
slap2_utils/functions/__init__.py
slap2_utils/functions/imagestacks.py
slap2_utils/functions/stim.py
slap2_utils/functions/tracefunctions.py
slap2_utils/subclasses/__init__.py
slap2_utils/subclasses/acquisitionContainer.py
slap2_utils/subclasses/metadata.py
slap2_utils/subclasses/slapROI.py
slap2_utils/utils/__init__.py
slap2_utils/utils/file_header.py
slap2_utils/utils/roi_utils.py
slap2_utils/utils/trace.py
slap2_utils/utils/trace_pixel.py
slap2_utils/utils/plots/__init__.py
slap2_utils/utils/plots/slap2Plots.py
slap2_utils-0.6.1.dist-info/METADATA
slap2_utils-0.6.1.dist-info/WHEEL
slap2_utils-0.6.1.dist-info/entry_points.txt
slap2_utils-0.6.1.dist-info/RECORD
slap2_utils-0.6.1.dist-info/licenses/LICENSE
