Metadata-Version: 2.4
Name: SLAP2_UTILS
Version: 0.6.1
Summary: Code to support using a SLAP2 Microscope
Project-URL: Homepage, https://github.com/Peter-Hogg/SLAP2_Utils
Project-URL: Issues, https://github.com/Peter-Hogg/SLAP2_Utils/issues
Author-email: Peter Hogg <peterhogg2006@gmail.com>, Jerry Tong <jerrytong0810@gmail.com>
License: MPL-2.0
License-File: LICENSE
Classifier: Development Status :: 4 - Beta
Classifier: Intended Audience :: Science/Research
Classifier: License :: OSI Approved :: Mozilla Public License 2.0 (MPL 2.0)
Classifier: Operating System :: OS Independent
Classifier: Programming Language :: Python :: 3
Classifier: Programming Language :: Python :: 3.9
Classifier: Programming Language :: Python :: 3.10
Classifier: Programming Language :: Python :: 3.11
Requires-Python: >=3.9
Requires-Dist: dask
Requires-Dist: h5py
Requires-Dist: matplotlib
Requires-Dist: numpy
Requires-Dist: pyneurotrace
Requires-Dist: pyqt6
Requires-Dist: scikit-image
Requires-Dist: scipy
Requires-Dist: vispy
Requires-Dist: zarr
Provides-Extra: cuda11x
Requires-Dist: cupy-cuda11x; extra == 'cuda11x'
Provides-Extra: cuda12x
Requires-Dist: cupy-cuda12x; extra == 'cuda12x'
Provides-Extra: cupy
Requires-Dist: cupy; extra == 'cupy'
Provides-Extra: examples
Requires-Dist: notebook; extra == 'examples'
